codequery/__init__.py
codequery/codequery.py
codequery/module.py
codequery-0.1.4.data/scripts/code-outline
codequery-0.1.4.data/scripts/code-profile
codequery-0.1.4.dist-info/LICENSE
codequery-0.1.4.dist-info/METADATA
codequery-0.1.4.dist-info/WHEEL
codequery-0.1.4.dist-info/top_level.txt
codequery-0.1.4.dist-info/RECORD
