Metadata-Version: 2.1
Name: codequery
Version: 0.1.4
Summary: Queries and code facts checking support for python source code
Home-page: https://github.com/daltonserey/codequery
Author: Dalton Serey
Author-email: daltonserey@gmail.com
Maintainer: Dalton Serey
Maintainer-email: daltonserey@gmail.com
License: MIT
Platform: UNKNOWN
Requires-Python: >3.6
License-File: LICENSE
